README.rst
setup.py
django_sluggee.egg-info/PKG-INFO
django_sluggee.egg-info/SOURCES.txt
django_sluggee.egg-info/dependency_links.txt
django_sluggee.egg-info/not-zip-safe
django_sluggee.egg-info/top_level.txt
sluggee/__init__.py
sluggee/six.py
sluggee/translit.py
sluggee/utils.py