Metadata-Version: 1.1
Name: django-sluggee
Version: 0.1
Summary: Russian slugifier for Django
Home-page: https://github.com/koorgoo/djangl-sluggee/
Author: Dima Kurguzov
Author-email: koorgoo@gmail.com
License: MIT
Keywords: django,slug
Platform: UNKNOWN
Classifier: Programming Language :: Python
Classifier: Topic :: Software Development :: Libraries :: Python Modules
Classifier: Framework :: Django
Classifier: Environment :: Web Environment
Classifier: Programming Language :: Python :: 2.6
Classifier: Programming Language :: Python :: 2.7
Classifier: Programming Language :: Python :: 3.2
Classifier: Programming Language :: Python :: 3.3
